pyproject_metadata/__init__.py
pyproject_metadata/py.typed
pyproject_metadata-0.8.1.dist-info/LICENSE
pyproject_metadata-0.8.1.dist-info/WHEEL
pyproject_metadata-0.8.1.dist-info/METADATA
pyproject_metadata-0.8.1.dist-info/RECORD
