Metadata-Version: 2.1
Name: pyproject-metadata
Version: 0.8.1
Summary: PEP 621 metadata parsing
Author-email: Filipe Laíns <lains@riseup.net>
Requires-Python: >=3.7
Classifier: License :: OSI Approved :: MIT License
Classifier: Programming Language :: Python :: 3
Classifier: Programming Language :: Python :: 3 :: Only
Classifier: Programming Language :: Python :: 3.7
Classifier: Programming Language :: Python :: 3.8
Classifier: Programming Language :: Python :: 3.9
Classifier: Programming Language :: Python :: 3.10
Classifier: Programming Language :: Python :: 3.11
Classifier: Programming Language :: Python :: 3.12
Classifier: Programming Language :: Python :: 3.13
Requires-Dist: packaging>=19.0
Requires-Dist: furo>=2023.9.10 ; extra == "docs"
Requires-Dist: sphinx-autodoc-typehints>=1.10.0 ; extra == "docs"
Requires-Dist: sphinx~=7.0 ; extra == "docs"
Requires-Dist: pytest-cov[toml]>=2 ; extra == "test"
Requires-Dist: pytest>=6.2.4 ; extra == "test"
Requires-Dist: tomli>=1.0.0 ; extra == "test" and (python_version<"3.11")
Project-URL: changelog, https://pep621.readthedocs.io/en/stable/changelog.html
Project-URL: homepage, https://github.com/pypa/pyproject-metadata
Provides-Extra: docs
Provides-Extra: test
